ollama_tool_register/__about__.py
ollama_tool_register/__init__.py
ollama_tool_register/tool_functions.py
ollama_tool_register-0.0.1.dist-info/METADATA
ollama_tool_register-0.0.1.dist-info/WHEEL
ollama_tool_register-0.0.1.dist-info/licenses/LICENSE.txt
ollama_tool_register-0.0.1.dist-info/RECORD
