Metadata-Version: 2.3
Name: ollama-tool-register
Version: 0.0.1
Summary: A complementary library to ollama-python to register your tools
Project-URL: Documentation, https://github.com/anthonywu/ollama-tool-register#readme
Project-URL: Issues, https://github.com/anthonywu/ollama-tool-register/issues
Project-URL: Source, https://github.com/anthonywu/ollama-tool-register
Author-email: Anthony Wu <please-file-gh-issue@noreply.example.com>
License-Expression: MIT
License-File: LICENSE.txt
Classifier: Development Status :: 3 - Alpha
Classifier: Programming Language :: Python
Classifier: Programming Language :: Python :: 3.9
Classifier: Programming Language :: Python :: 3.10
Classifier: Programming Language :: Python :: 3.11
Classifier: Programming Language :: Python :: 3.12
Classifier: Programming Language :: Python :: Implementation :: CPython
Classifier: Programming Language :: Python :: Implementation :: PyPy
Requires-Python: >=3.9
Requires-Dist: ollama
Provides-Extra: dev
Requires-Dist: pytest>=8.3.0; extra == 'dev'
